boolean_gene/__init__.py
boolean_gene/cli.py
boolean_gene/run_clustering_analysis.py
boolean_gene/run_count_loops.py
boolean_gene/run_lyapunov_analysis.py
boolean_gene/run_stability_analysis.py
boolean_gene/modules/BooleanNetwork.py
boolean_gene/modules/__init__.py
boolean_gene/modules/analysis.py
boolean_gene/modules/canalizing_analysis.py
boolean_gene/modules/formula_parser.py
boolean_gene/modules/io_utils.py
boolean_gene/modules/logic_processing.py
boolean_gene/modules/qm.py
boolean_gene/modules/regenerate_network.py
boolean_gene-0.0.1.dist-info/METADATA
boolean_gene-0.0.1.dist-info/WHEEL
boolean_gene-0.0.1.dist-info/entry_points.txt
boolean_gene-0.0.1.dist-info/top_level.txt
boolean_gene-0.0.1.dist-info/RECORD
