Metadata-Version: 2.4
Name: boolean_gene
Version: 0.0.1
Summary: Analysis of Boolean gene networks
Author: Chris Viets
Project-URL: Homepage, https://github.com/cviets/BooleanGene
Project-URL: Bug Tracker, https://github.com/cviets/BooleanGene/issues
Requires-Python: >=3.6
Requires-Dist: numpy
Requires-Dist: networkx
Requires-Dist: sympy
Requires-Dist: tqdm
